verse_sdk/__init__.py
verse_sdk/decorators.py
verse_sdk/sdk.py
verse_sdk/sdk_builder.py
verse_sdk/utils.py
verse_sdk/contexts/__init__.py
verse_sdk/contexts/base.py
verse_sdk/contexts/generation.py
verse_sdk/contexts/span.py
verse_sdk/contexts/trace.py
verse_sdk/contexts/types.py
verse_sdk/contexts/utils.py
verse_sdk/exporters/__init__.py
verse_sdk/exporters/base.py
verse_sdk/exporters/types.py
verse_sdk/exporters/console/__init__.py
verse_sdk/exporters/console/exporter.py
verse_sdk/exporters/langfuse/__init__.py
verse_sdk/exporters/langfuse/constants.py
verse_sdk/exporters/langfuse/exporter.py
verse_sdk/exporters/langfuse/types.py
verse_sdk/exporters/otel/__init__.py
verse_sdk/exporters/otel/constants.py
verse_sdk/exporters/otel/exporter.py
verse_sdk/exporters/otel/types.py
verse_sdk/exporters/verse/__init__.py
verse_sdk/exporters/verse/constants.py
verse_sdk/exporters/verse/exporter.py
verse_sdk/exporters/verse/types.py
verse_sdk/exporters/verse/utils.py
verse_sdk/integrations/__init__.py
verse_sdk/integrations/langchain/__init__.py
verse_sdk/integrations/langchain/configure.py
verse_sdk/integrations/langchain/utils.py
verse_sdk/integrations/litellm/__init__.py
verse_sdk/integrations/litellm/configure.py
verse_sdk/integrations/litellm/utils.py
verse_sdk/integrations/pydantic_ai/__init__.py
verse_sdk/integrations/pydantic_ai/constants.py
verse_sdk/integrations/pydantic_ai/patch.py
verse_sdk/integrations/pydantic_ai/utils.py
verse_sdk/processors/__init__.py
verse_sdk/processors/attribute.py
verse_sdk/processors/attribute_batch.py
verse_sdk/wrappers/__init__.py
verse_sdk/wrappers/scope_filter.py
verse_sdk-0.2.0.dist-info/METADATA
verse_sdk-0.2.0.dist-info/WHEEL
verse_sdk-0.2.0.dist-info/licenses/LICENSE
verse_sdk-0.2.0.dist-info/RECORD
