Metadata-Version: 2.4
Name: verse-sdk
Version: 0.2.0
Summary: Verse Python SDK
License: MIT
License-File: LICENSE
Requires-Python: >=3.12
Requires-Dist: cuid2>=2.0.1
Requires-Dist: opentelemetry-api>=1.34.1
Requires-Dist: opentelemetry-exporter-otlp[logs]>=1.34.1
Requires-Dist: opentelemetry-instrumentation-logging>=0.44.0
Requires-Dist: opentelemetry-instrumentation>=0.44.0
Requires-Dist: opentelemetry-sdk[logs]<1.35.0,>=1.34.1
Requires-Dist: requests>=2.31.0
